<?xml version="1.0"?>
<!DOCTYPE emulator SYSTEM "../../../dtd/caesar.dtd">
<emulator id="rishgar" type="single" dat="Rishgar_v0.92b">
	<name>Rishgar (Ishmair's RYGAR Emulator)</name>
	<version>0.92b</version>
	<date>17/06/1997</date>

	<homepage status="none"></homepage>
	<author_link id="ishmair">&author_ishmair;</author_link>

	<emulates>Legendary Warrior RYGAR (Tecmo)</emulates>
	<comment>The better of the two Rygar emulators (the other one being REM!)</comment>
	<status>Dormant</status>

	<cpu_links>
		<library_link id="maze" type="cpu">&library_maze;</library_link>
	</cpu_links>

	<platform>DOS</platform>

	<controllers>
		<controller>Keyboard</controller>
		<controller>Joystick</controller>
	</controllers>

	<features>
		<sound>Yes</sound>
		<source>No</source>
		<screendump>No</screendump>
		<hiscoresave>No</hiscoresave>
		<savegame>No</savegame>
		<recordinput>No</recordinput>
		<dips>Yes</dips>
		<cheat>No</cheat>
		<autoframeskip>No</autoframeskip>
		<throttle>Yes</throttle>
	</features>

	<files>
		<file name="rishgar.zip">Emulator</file>
	</files>
</emulator>
