<?xml version="1.0"?>
<!DOCTYPE emulator SYSTEM "../../../dtd/caesar.dtd">
<emulator id="mame64" type="n64" dat="dummy">
	<name>MAME64</name>
	<version>?</version>
	<date>11/11/1997</date>

	<homepage status="none"></homepage>
	<author_link id="rbubba">&author_rbubba;</author_link>

	<emulates>Emulates only a few early MAME games</emulates>
	<comment>MAME64 was abandoned early on in it's life due to people leaking it out against the author's wishes. The distribution included the game ROMs within it so you will not find any sites hosting it.</comment>
	<status>Discontinued</status>

	<platform>N64</platform>

	<controllers>
		<controller>Joypad</controller>
	</controllers>

	<features>
		<sound>?</sound>
		<source>No</source>
		<screendump>No</screendump>
		<hiscoresave>No</hiscoresave>
		<savegame>No</savegame>
		<recordinput>No</recordinput>
		<dips>?</dips>
		<cheat>No</cheat>
		<autoframeskip>No</autoframeskip>
		<throttle>?</throttle>
		<network>No</network>
		<recordsound>No</recordsound>
		<rotate>?</rotate>
	</features>

	<relatives>
		<port_of>
			<emulator_link id="mame" type="multi">&emulator_mame;</emulator_link>
		</port_of>
	</relatives>
</emulator>
