<?xml version="1.0"?>
<!DOCTYPE emulator SYSTEM "../../../dtd/caesar.dtd">
<emulator id="xdragon" type="multi" dat="xDragon_v0.30">
	<name>xDragon</name>
	<version>0.30</version>
	<date>06/05/1998</date>

	<homepage>http://membres.lycos.fr/gouky/xdragon/</homepage>
	<author_link id="nicholas_hamel">&author_nicholas_hamel;</author_link>
	<author_link id="david_mitchel">&author_david_mitchel;</author_link>

	<emulates>Data East games</emulates>
	<comment>By the author of xNES. Sound missing in a couple of Slay Spy and Midnight Resistance</comment>
	<status>Dormant</status>

	<cpu_links>
		<library_link id="starscream" type="cpu">&library_starscream;</library_link>
	</cpu_links>

	<tool_links>
		<tool_link id="djgpp" type="compilers">&tool_djgpp;</tool_link>
		<tool_link id="allegro" type="gfx_libs">&tool_allegro;</tool_link>
	</tool_links>

	<platform>DOS</platform>

	<controllers>
		<controller>Keyboard</controller>
		<controller>Joystick</controller>
	</controllers>

	<features>
		<sound>Yes</sound>
		<source>No</source>
		<screendump>Yes</screendump>
		<hiscoresave>No</hiscoresave>
		<savegame>No</savegame>
		<recordinput>No</recordinput>
		<dips>Yes</dips>
		<cheat>No</cheat>
		<autoframeskip>Yes</autoframeskip>
		<throttle>Yes</throttle>
		<network>No</network>
		<recordsound>No</recordsound>
		<rotate>Yes</rotate>
	</features>

	<files>
		<file name="xdragon030.zip">Emulator</file>
	</files>
</emulator>
